<?xml version="1.0" encoding="UTF-8" ?>
<!DOCTYPE mapper PUBLIC "-//mybatis.org//DTD Mapper 3.0//EN" "http://mybatis.org/dtd/mybatis-3-mapper.dtd" >
<mapper namespace="com.glens.pwCloudOs.pm.taskMgr.device.dao.PowerDeviceTypeMapper" >
  <resultMap id="BaseResultMap" type="com.glens.pwCloudOs.pm.taskMgr.device.vo.PowerDeviceType" >
    <!--
      WARNING - @mbggenerated
      This element is automatically generated by MyBatis Generator, do not modify.
    -->
    <id column="rowid" property="rowid" jdbcType="BIGINT" />
    <result column="DEVICE_TYPE_CODE" property="deviceTypeCode" jdbcType="VARCHAR" />
    <result column="DEVICE_TYPE_NAME" property="deviceTypeName" jdbcType="VARCHAR" />
    <result column="SYS_CREATE_TIME" property="sysCreateTime" jdbcType="TIMESTAMP" />
    <result column="SYS_UPDATE_TIME" property="sysUpdateTime" jdbcType="TIMESTAMP" />
    <result column="SYS_DELETE_TIME" property="sysDeleteTime" jdbcType="TIMESTAMP" />
    <result column="SYS_PROCESS_FLAG" property="sysProcessFlag" jdbcType="CHAR" />
    <result column="REMARKS" property="remarks" jdbcType="VARCHAR" />
  </resultMap>
  <sql id="Base_Column_List" >
    <!--
      WARNING - @mbggenerated
      This element is automatically generated by MyBatis Generator, do not modify.
    -->
    rowid, DEVICE_TYPE_CODE, DEVICE_TYPE_NAME, SYS_CREATE_TIME, SYS_UPDATE_TIME, SYS_DELETE_TIME, 
    SYS_PROCESS_FLAG, REMARKS
  </sql>
  <select id="findById" resultMap="BaseResultMap" parameterType="java.lang.Long" >
    <!--
      WARNING - @mbggenerated
      This element is automatically generated by MyBatis Generator, do not modify.
    -->
    select 
    <include refid="Base_Column_List" />
    from power_device_type
    where rowid = #{rowid,jdbcType=BIGINT}
  </select>
  <delete id="delete" parameterType="java.lang.Long" >
    <!--
      WARNING - @mbggenerated
      This element is automatically generated by MyBatis Generator, do not modify.
    -->
    delete from power_device_type
    where rowid = #{rowid,jdbcType=BIGINT}
  </delete>
  <insert id="insert" parameterType="com.glens.pwCloudOs.pm.taskMgr.device.vo.PowerDeviceType" >
    <!--
      WARNING - @mbggenerated
      This element is automatically generated by MyBatis Generator, do not modify.
    -->
    insert into power_device_type (rowid, DEVICE_TYPE_CODE, DEVICE_TYPE_NAME, 
      SYS_CREATE_TIME, SYS_UPDATE_TIME, SYS_DELETE_TIME, 
      SYS_PROCESS_FLAG, REMARKS)
    values (#{rowid,jdbcType=BIGINT}, #{deviceTypeCode,jdbcType=VARCHAR}, #{deviceTypeName,jdbcType=VARCHAR}, 
      #{sysCreateTime,jdbcType=TIMESTAMP}, #{sysUpdateTime,jdbcType=TIMESTAMP}, #{sysDeleteTime,jdbcType=TIMESTAMP}, 
      #{sysProcessFlag,jdbcType=CHAR}, #{remarks,jdbcType=VARCHAR})
  </insert>
  <insert id="insertSelective" parameterType="com.glens.pwCloudOs.pm.taskMgr.device.vo.PowerDeviceType" >
    <!--
      WARNING - @mbggenerated
      This element is automatically generated by MyBatis Generator, do not modify.
    -->
    insert into power_device_type
    <trim prefix="(" suffix=")" suffixOverrides="," >
      <if test="rowid != null" >
        rowid,
      </if>
      <if test="deviceTypeCode != null" >
        DEVICE_TYPE_CODE,
      </if>
      <if test="deviceTypeName != null" >
        DEVICE_TYPE_NAME,
      </if>
      <if test="sysCreateTime != null" >
        SYS_CREATE_TIME,
      </if>
      <if test="sysUpdateTime != null" >
        SYS_UPDATE_TIME,
      </if>
      <if test="sysDeleteTime != null" >
        SYS_DELETE_TIME,
      </if>
      <if test="sysProcessFlag != null" >
        SYS_PROCESS_FLAG,
      </if>
      <if test="remarks != null" >
        REMARKS,
      </if>
    </trim>
    <trim prefix="values (" suffix=")" suffixOverrides="," >
      <if test="rowid != null" >
        #{rowid,jdbcType=BIGINT},
      </if>
      <if test="deviceTypeCode != null" >
        #{deviceTypeCode,jdbcType=VARCHAR},
      </if>
      <if test="deviceTypeName != null" >
        #{deviceTypeName,jdbcType=VARCHAR},
      </if>
      <if test="sysCreateTime != null" >
        #{sysCreateTime,jdbcType=TIMESTAMP},
      </if>
      <if test="sysUpdateTime != null" >
        #{sysUpdateTime,jdbcType=TIMESTAMP},
      </if>
      <if test="sysDeleteTime != null" >
        #{sysDeleteTime,jdbcType=TIMESTAMP},
      </if>
      <if test="sysProcessFlag != null" >
        #{sysProcessFlag,jdbcType=CHAR},
      </if>
      <if test="remarks != null" >
        #{remarks,jdbcType=VARCHAR},
      </if>
    </trim>
  </insert>
  <update id="update" parameterType="com.glens.pwCloudOs.pm.taskMgr.device.vo.PowerDeviceType" >
    <!--
      WARNING - @mbggenerated
      This element is automatically generated by MyBatis Generator, do not modify.
    -->
    update power_device_type
    <set >
      <if test="deviceTypeCode != null" >
        DEVICE_TYPE_CODE = #{deviceTypeCode,jdbcType=VARCHAR},
      </if>
      <if test="deviceTypeName != null" >
        DEVICE_TYPE_NAME = #{deviceTypeName,jdbcType=VARCHAR},
      </if>
      <if test="sysCreateTime != null" >
        SYS_CREATE_TIME = #{sysCreateTime,jdbcType=TIMESTAMP},
      </if>
      <if test="sysUpdateTime != null" >
        SYS_UPDATE_TIME = #{sysUpdateTime,jdbcType=TIMESTAMP},
      </if>
      <if test="sysDeleteTime != null" >
        SYS_DELETE_TIME = #{sysDeleteTime,jdbcType=TIMESTAMP},
      </if>
      <if test="sysProcessFlag != null" >
        SYS_PROCESS_FLAG = #{sysProcessFlag,jdbcType=CHAR},
      </if>
      <if test="remarks != null" >
        REMARKS = #{remarks,jdbcType=VARCHAR},
      </if>
    </set>
    where rowid = #{rowid,jdbcType=BIGINT}
  </update>
  <update id="updateByPrimaryKey" parameterType="com.glens.pwCloudOs.pm.taskMgr.device.vo.PowerDeviceType" >
    <!--
      WARNING - @mbggenerated
      This element is automatically generated by MyBatis Generator, do not modify.
    -->
    update power_device_type
    set DEVICE_TYPE_CODE = #{deviceTypeCode,jdbcType=VARCHAR},
      DEVICE_TYPE_NAME = #{deviceTypeName,jdbcType=VARCHAR},
      SYS_CREATE_TIME = #{sysCreateTime,jdbcType=TIMESTAMP},
      SYS_UPDATE_TIME = #{sysUpdateTime,jdbcType=TIMESTAMP},
      SYS_DELETE_TIME = #{sysDeleteTime,jdbcType=TIMESTAMP},
      SYS_PROCESS_FLAG = #{sysProcessFlag,jdbcType=CHAR},
      REMARKS = #{remarks,jdbcType=VARCHAR}
    where rowid = #{rowid,jdbcType=BIGINT}
  </update>
  <select id="queryForList" parameterType="map" resultMap="BaseResultMap">
  select * 
  from power_device_type
  </select>
  <select id="queryForCount" parameterType="map" resultType="int">
  select count(*)
  from power_device_type
  </select>
  <select id="queryForPage" parameterType="map" resultMap="BaseResultMap">
  select *
  from power_device_type
  limit #{firstResult},#{maxResult} 
  </select>
</mapper>